foldcomp/__init__.py
foldcomp/foldcomp.cp39-win_amd64.pyd
foldcomp/foldcomp.py
foldcomp/setup.py
foldcomp/util.py
foldcomp-0.1.0.data/data/include/dirent.h
foldcomp-0.1.0.dist-info/licenses/LICENSE.txt
foldcomp-0.1.0.dist-info/METADATA
foldcomp-0.1.0.dist-info/WHEEL
foldcomp-0.1.0.dist-info/top_level.txt
foldcomp-0.1.0.dist-info/RECORD
