Metadata-Version: 2.1
Name: foldcomp
Version: 0.1.0
Summary: Foldcomp compresses protein structures with torsion angles effectively. It compresses the backbone atoms to 8 bytes and the side chain to additionally 4-5 byes per residue, an averaged-sized protein of 350 residues requires ~4.2kb. Foldcomp is a C++ library with Python bindings.
Author: Milot Mirdita <milot@mirdita.de>, Hyunbin Kim <khb7840@gmail.com>, Martin Steinegger <themartinsteinegger@gmail.com>
License: GPLv3
Requires-Python: >=3.7
License-File: LICENSE.txt
Requires-Dist: httpx>=0.23.0
Provides-Extra: test
Requires-Dist: pytest; extra == "test"
